LICENSE
mimetype_more/002-mime-all-types.json
mimetype_more/003-mime-extra.json
mimetype_more/_001_http_common_mime_types.py
mimetype_more/_002_mime_all_types.py
mimetype_more/_003_mime_extra.py
mimetype_more/__init__.py
mimetype_more/py.typed
mimetype_more-0.0.1.dist-info/LICENSE
mimetype_more-0.0.1.dist-info/METADATA
mimetype_more-0.0.1.dist-info/WHEEL
mimetype_more-0.0.1.dist-info/RECORD
